infobip_api_client/__init__.py
infobip_api_client/api_client.py
infobip_api_client/api_response.py
infobip_api_client/configuration.py
infobip_api_client/exceptions.py
infobip_api_client/py.typed
infobip_api_client/rest.py
infobip_api_client/api/__init__.py
infobip_api_client/api/call_routing_api.py
infobip_api_client/api/calls_api.py
infobip_api_client/api/click_to_call_api.py
infobip_api_client/api/email_api.py
infobip_api_client/api/flow_api.py
infobip_api_client/api/forms_api.py
infobip_api_client/api/number_masking_api.py
infobip_api_client/api/sms_api.py
infobip_api_client/api/tfa_api.py
infobip_api_client/api/voice_api.py
infobip_api_client/models/__init__.py
infobip_api_client/models/api_error.py
infobip_api_client/models/api_error_resource.py
infobip_api_client/models/api_error_violation.py
infobip_api_client/models/api_exception.py
infobip_api_client/models/api_request_error.py
infobip_api_client/models/api_request_error_details.py
infobip_api_client/models/basic_security_config.py
infobip_api_client/models/call.py
infobip_api_client/models/call_bulk_request.py
infobip_api_client/models/call_bulk_response.py
infobip_api_client/models/call_bulk_status.py
infobip_api_client/models/call_direction.py
infobip_api_client/models/call_endpoint.py
infobip_api_client/models/call_endpoint_type.py
infobip_api_client/models/call_log.py
infobip_api_client/models/call_log_page.py
infobip_api_client/models/call_page.py
infobip_api_client/models/call_rate.py
infobip_api_client/models/call_recording.py
infobip_api_client/models/call_recording_page.py
infobip_api_client/models/call_recording_request.py
infobip_api_client/models/call_request.py
infobip_api_client/models/call_routing_criteria.py
infobip_api_client/models/call_routing_criteria_type.py
infobip_api_client/models/call_routing_custom_data_entry.py
infobip_api_client/models/call_routing_destination.py
infobip_api_client/models/call_routing_destination_type.py
infobip_api_client/models/call_routing_endpoint.py
infobip_api_python_client-5.1.1.dist-info/licenses/LICENSE
infobip_api_python_client-5.1.1.dist-info/METADATA
infobip_api_python_client-5.1.1.dist-info/WHEEL
infobip_api_python_client-5.1.1.dist-info/top_level.txt
infobip_api_python_client-5.1.1.dist-info/RECORD
