Metadata-Version: 2.4
Name: infobip-api-python-client
Version: 5.1.1
Summary: This is a Python package for Infobip API and you can use it as a dependency to add Infobip APIs to your application.
Home-page: https://pypi.org/project/infobip-api-python-client
Author: Infobip support
Author-email: support@infobip.com
Keywords: infobip,sms,tfa,2fa,calls,voice,sdk,rest,api,openapi
License-File: LICENSE
Requires-Dist: urllib3<2.1.0,>=1.25.3
Requires-Dist: python_dateutil>=2.5.3
Requires-Dist: setuptools>=72.1.0
Requires-Dist: pydantic>=2
Requires-Dist: typing-extensions>=4.7.1
Dynamic: author
Dynamic: author-email
Dynamic: description
Dynamic: description-content-type
Dynamic: home-page
Dynamic: keywords
Dynamic: license-file
Dynamic: requires-dist
Dynamic: summary
